do_dpc/__init__.py
do_dpc/control_utils/__init__.py
do_dpc/control_utils/control_structs.py
do_dpc/control_utils/lti_systems.py
do_dpc/control_utils/noise_generators.py
do_dpc/control_utils/pid.py
do_dpc/control_utils/pid_control_utils.py
do_dpc/control_utils/pid_profiles.py
do_dpc/control_utils/trajectory_collector.py
do_dpc/dpc/__init__.py
do_dpc/dpc/deepc.py
do_dpc/dpc/dpc.py
do_dpc/dpc/dpc_structs.py
do_dpc/dpc/dpc_utils.py
do_dpc/dpc/gamma_ddpc.py
do_dpc/dpc/mpc.py
do_dpc/dpc/mpc_nfour_sid.py
do_dpc/dpc/mpc_oracle.py
do_dpc/dpc/spc.py
do_dpc/dpc/tpc.py
do_dpc/environments/__init__.py
do_dpc/environments/legacy_coco_rocket/__init__.py
do_dpc/environments/legacy_coco_rocket/env_cfg.py
do_dpc/environments/legacy_coco_rocket/rocketlander.py
do_dpc/environments/legacy_coco_rocket/system_model.py
do_dpc/environments/rocket_env/__init__.py
do_dpc/environments/rocket_env/rocket_controller_profiles.py
do_dpc/environments/rocket_env/rocket_data_collection.py
do_dpc/environments/rocket_env/rocket_env_cfg_facade.py
do_dpc/environments/rocket_env/rocket_env_facade.py
do_dpc/environments/rocket_env/rocket_utils.py
do_dpc/utils/__init__.py
do_dpc/utils/logging_config.py
do_dpc/utils/path_manager.py
do_dpc/utils/plots.py
do_dpc/utils/serialization.py
do_dpc-1.0.0.dist-info/licenses/LICENSE.txt
tests/__init__.py
tests/fixtures/__init__.py
tests/fixtures/utils_fixtures.py
tests/system_tests/__init__.py
tests/system_tests/test_basic_functionality.py
tests/system_tests/test_deepc.py
tests/system_tests/test_dpc_controllers.py
tests/system_tests/test_maps.py
tests/system_tests/test_rocket_systems.py
tests/system_tests/util_functions.py
tests/unit_tests/__init__.py
tests/unit_tests/test_control_data_collector.py
tests/unit_tests/test_control_parameters.py
tests/unit_tests/test_logging_config.py
tests/unit_tests/test_lti_simulator.py
tests/unit_tests/test_path_manager.py
tests/unit_tests/test_pid_controller.py
tests/unit_tests/test_serialization.py
tests/unit_tests/test_white_noise_generator.py
do_dpc-1.0.0.dist-info/METADATA
do_dpc-1.0.0.dist-info/WHEEL
do_dpc-1.0.0.dist-info/top_level.txt
do_dpc-1.0.0.dist-info/RECORD
