Metadata-Version: 2.4
Name: do-dpc
Version: 1.0.0
Summary: Framework software package for the Data-Driven Predictive Control (DPC) algorithm with visual examples.
Home-page: https://github.com/do-dpc/do-dpc
Author: Sebastian Graf
Author-email: sebastian.graf@gmx.ch
Classifier: Programming Language :: Python :: 3
Classifier: License :: OSI Approved :: GNU Lesser General Public License v3 (LGPLv3)
Classifier: Operating System :: OS Independent
Requires-Python: >=3.12
License-File: LICENSE.txt
Requires-Dist: pylint~=3.3.3
Requires-Dist: pytest~=8.3.4
Requires-Dist: pytest-cov~=6.0.0
Requires-Dist: numpy~=1.26.4
Requires-Dist: scipy~=1.15.1
Requires-Dist: black~=25.1.0
Requires-Dist: mypy~=1.15.0
Requires-Dist: pre-commit~=4.1.0
Requires-Dist: cvxpy~=1.6.0
Requires-Dist: onnx>=1.13.0
Requires-Dist: ipykernel~=6.29.5
Requires-Dist: packaging~=24.2
Requires-Dist: asyncua~=1.1.5
Requires-Dist: control~=0.10.1
Requires-Dist: gymnasium~=1.1.1
Requires-Dist: pygame~=2.6.1
Requires-Dist: box2d-py~=2.3.8
Requires-Dist: moviepy~=2.1.2
Requires-Dist: matplotlib~=3.10.0
Requires-Dist: ipython~=8.32.0
Requires-Dist: PyVirtualDisplay~=3.0
Requires-Dist: tqdm~=4.67.1
Dynamic: author
Dynamic: author-email
Dynamic: classifier
Dynamic: description
Dynamic: description-content-type
Dynamic: home-page
Dynamic: license-file
Dynamic: requires-dist
Dynamic: requires-python
Dynamic: summary
